{"nodes": [{"id": "users_xiong_gao_code_github_pythons_01_docs_11_\u6a21\u5757_md", "label": "11.\u6a21\u5757.md", "file_type": "document", "source_file": "/Users/xiong.gao/code/GITHUB/pythons/01-docs/11.\u6a21\u5757.md", "source_location": "L1"}, {"id": "01_docs_11_\u6a21\u5757_\u6a21\u5757\u7684\u5b9a\u4e49", "label": "\u6a21\u5757\u7684\u5b9a\u4e49", "file_type": "document", "source_file": "/Users/xiong.gao/code/GITHUB/pythons/01-docs/11.\u6a21\u5757.md", "source_location": "L3"}, {"id": "01_docs_11_\u6a21\u5757_\u5185\u7f6e\u6a21\u5757\u6709\u54ea\u4e9b", "label": "\u5185\u7f6e\u6a21\u5757\u6709\u54ea\u4e9b", "file_type": "document", "source_file": "/Users/xiong.gao/code/GITHUB/pythons/01-docs/11.\u6a21\u5757.md", "source_location": "L12"}, {"id": "01_docs_11_\u6a21\u5757_\u6a21\u5757\u7684\u5bfc\u5165", "label": "\u6a21\u5757\u7684\u5bfc\u5165", "file_type": "document", "source_file": "/Users/xiong.gao/code/GITHUB/pythons/01-docs/11.\u6a21\u5757.md", "source_location": "L14"}, {"id": "01_docs_11_\u6a21\u5757_\u8f6f\u4ef6\u5305_package", "label": "\u8f6f\u4ef6\u5305 package", "file_type": "document", "source_file": "/Users/xiong.gao/code/GITHUB/pythons/01-docs/11.\u6a21\u5757.md", "source_location": "L16"}], "edges": [{"source": "users_xiong_gao_code_github_pythons_01_docs_11_\u6a21\u5757_md", "target": "01_docs_11_\u6a21\u5757_\u6a21\u5757\u7684\u5b9a\u4e49", "relation": "contains", "confidence": "EXTRACTED", "source_file": "/Users/xiong.gao/code/GITHUB/pythons/01-docs/11.\u6a21\u5757.md", "source_location": "L3", "weight": 1.0}, {"source": "users_xiong_gao_code_github_pythons_01_docs_11_\u6a21\u5757_md", "target": "01_docs_11_\u6a21\u5757_\u5185\u7f6e\u6a21\u5757\u6709\u54ea\u4e9b", "relation": "contains", "confidence": "EXTRACTED", "source_file": "/Users/xiong.gao/code/GITHUB/pythons/01-docs/11.\u6a21\u5757.md", "source_location": "L12", "weight": 1.0}, {"source": "users_xiong_gao_code_github_pythons_01_docs_11_\u6a21\u5757_md", "target": "01_docs_11_\u6a21\u5757_\u6a21\u5757\u7684\u5bfc\u5165", "relation": "contains", "confidence": "EXTRACTED", "source_file": "/Users/xiong.gao/code/GITHUB/pythons/01-docs/11.\u6a21\u5757.md", "source_location": "L14", "weight": 1.0}, {"source": "users_xiong_gao_code_github_pythons_01_docs_11_\u6a21\u5757_md", "target": "01_docs_11_\u6a21\u5757_\u8f6f\u4ef6\u5305_package", "relation": "contains", "confidence": "EXTRACTED", "source_file": "/Users/xiong.gao/code/GITHUB/pythons/01-docs/11.\u6a21\u5757.md", "source_location": "L16", "weight": 1.0}], "input_tokens": 0, "output_tokens": 0}